README.md
setup.py
PyJSONCanvas.egg-info/PKG-INFO
PyJSONCanvas.egg-info/SOURCES.txt
PyJSONCanvas.egg-info/dependency_links.txt
PyJSONCanvas.egg-info/top_level.txt
pyjsoncanvas/__init__.py
pyjsoncanvas/encoder.py
pyjsoncanvas/exceptions.py
pyjsoncanvas/jsoncanvas.py
pyjsoncanvas/models.py
pyjsoncanvas/utils.py
pyjsoncanvas/validate.py
pyjsoncanvas.egg-info/PKG-INFO
pyjsoncanvas.egg-info/SOURCES.txt
pyjsoncanvas.egg-info/dependency_links.txt
pyjsoncanvas.egg-info/top_level.txt