Metadata-Version: 2.1
Name: PyJSONCanvas
Version: 1.0.2
Summary: A simple library for working with JSON Canvas (previously known as Obsidian Canvas) files.
Home-page: https://github.com/CheeksTheGeek/PyJSONCanvas
Author: Chaitanya Sharma
License: MIT
